
{"items":[{"name":"CliTester.Exceptions","href":"CliTester.Exceptions.html","topicHref":"CliTester.Exceptions.html","topicUid":"CliTester.Exceptions","items":[{"name":"ValueMismatchException","href":"CliTester.Exceptions.ValueMismatchException.html","topicHref":"CliTester.Exceptions.ValueMismatchException.html","topicUid":"CliTester.Exceptions.ValueMismatchException"}]},{"name":"CliTester.Instances","href":"CliTester.Instances.html","topicHref":"CliTester.Instances.html","topicUid":"CliTester.Instances","items":[{"name":"Fixture","href":"CliTester.Instances.Fixture.html","topicHref":"CliTester.Instances.Fixture.html","topicUid":"CliTester.Instances.Fixture"},{"name":"FixtureConditional<TDelegate>","href":"CliTester.Instances.FixtureConditional-1.html","topicHref":"CliTester.Instances.FixtureConditional-1.html","topicUid":"CliTester.Instances.FixtureConditional`1"},{"name":"FixtureUnconditional<TDelegate>","href":"CliTester.Instances.FixtureUnconditional-1.html","topicHref":"CliTester.Instances.FixtureUnconditional-1.html","topicUid":"CliTester.Instances.FixtureUnconditional`1"}]},{"name":"CliTester.Tools","href":"CliTester.Tools.html","topicHref":"CliTester.Tools.html","topicUid":"CliTester.Tools","items":[{"name":"FixtureRunner","href":"CliTester.Tools.FixtureRunner.html","topicHref":"CliTester.Tools.FixtureRunner.html","topicUid":"CliTester.Tools.FixtureRunner"}]}],"memberLayout":"SamePage"}
